mpn/__about__.py
mpn/__init__.py
mpn/__main__.py
mpn/python_help.py
mpn-0.0.1.dist-info/METADATA
mpn-0.0.1.dist-info/WHEEL
mpn-0.0.1.dist-info/entry_points.txt
mpn-0.0.1.dist-info/licenses/LICENSE
mpn-0.0.1.dist-info/RECORD
